{
  "general.prev": "Previous",
  "general.next": "Next",
  "general.result": "Result",
  "general.regex": "Regex",
  "general.text": "Text",
  "general.watch": "Watch",
  "general.start": "Start",
  "general.continue": "Continue",
  "general.completedStep": "Step Completed!",
  "general.hintQuestion": "Show Answer",
  "general.reportStep": "Report a Problem",
  "general.startLearning": "Start Learning",
  "general.comingSoon": "Coming Soon",
  "general.becomeSponsor": "Become a Sponsor",
  "general.learn": "Learn",
  "general.playground": "Playground",
  "general.cheatsheet": "Cheatsheet",
  "general.ourSponsors": "Our Sponsors",
  "general.share": "Share",
  "general.shareLinkCopied": "Share link copied!",
  "general.somethingWentWrong": "Something went wrong!",

  "notFound.intro": "The page you are looking for does not exist.",
  "notFound.button": "Back to home",

  "page.landing.title": "Regex Learn - Step by step, from zero to advanced.",
  "page.learn.title": "Regex Learn - Regex Interactive Course",
  "page.cheatsheet.title": "Regex Learn - Regex Cheatsheet",
  "page.playground.title": "Regex Learn - Playground",
  "page.404.title": "Regex Learn - Not Found",

  "page.landing.description": "Learn Regex interactively, practice at your level, test and share your own Regex.",
  "page.learn.description": "Learn Regex step by step. Complete the interactive tutorial that will make your learning easier and faster.",
  "page.cheatsheet.description": "Sometimes you just need to remember Regex. Try the cheatsheet that will make it easier for you to understand and remember better.",
  "page.playground.description": "You can easily build and test your regex pattern online via Playground.",

  "learn.safari.unsupportWarning": "Regex in this step is not supported by some browsers. If you have trouble getting past this step, click here."
}
